{
  "children": [
    {
      "children": [
        {
          "children": [
            {
              "degree": "subcategory",
              "keywords": [
                "assassin",
                "game",
                "halo",
                "play",
                "redempt",
                "twitch",
                "witcher"
              ],
              "name": "gaming",
              "q_idx": 0,
              "question": [
                "What laptop brand are you looking for?",
                "Sorry we do no have them at the momment"
              ]
            },
            {
              "degree": "subcategory",
              "keywords": [
                "assign",
                "busi",
                "compani",
                "confer",
                "holiday",
                "homework",
                "job",
                "lectur",
                "note",
                "offic",
                "research",
                "school",
                "student",
                "studi",
                "travel",
                "trip",
                "tutori",
                "univers",
                "work"
              ],
              "name": "business",
              "q_idx": 0,
              "question": [
                "what laptop brand are you looking for?",
                "Sorry this brand is unavailable right now can you pick another brand?"
              ]
            }
          ],
          "degree": "category",
          "keywords": [
            "acer",
            "air",
            "alienwar",
            "appl",
            "aspir",
            "assassin",
            "assign",
            "axim",
            "busi",
            "compani",
            "compaq",
            "comput",
            "confer",
            "dell",
            "dimens",
            "dv",
            "edg",
            "fujitsu",
            "game",
            "halo",
            "holiday",
            "homework",
            "hp",
            "ibm",
            "ibook",
            "inspiron",
            "job",
            "laptop",
            "latitud",
            "lectur",
            "lenovo",
            "macbook",
            "mp",
            "mx",
            "nc",
            "netbook",
            "note",
            "notebook",
            "offic",
            "pavilion",
            "pc",
            "play",
            "player",
            "powerbook",
            "pro",
            "redempt",
            "research",
            "school",
            "soni",
            "student",
            "studi",
            "studio",
            "thinkpad",
            "timelin",
            "travel",
            "trip",
            "tutori",
            "twitch",
            "ultraport",
            "univers",
            "vaio",
            "witcher",
            "work",
            "xv"
          ],
          "name": "laptop",
          "q_idx": 0,
          "question": [
            "What will you use the laptop for?",
            "sorry we do not have what you typed can we offer you other laptops?"
          ]
        },
        {
          "children": [
            {
              "degree": "subcategory",
              "keywords": [
                "agenc",
                "airfar",
                "airlin",
                "budget",
                "channel",
                "cheap",
                "destin",
                "fare",
                "flight",
                "hotel",
                "last",
                "minut",
                "news",
                "one",
                "packag",
                "plane",
                "site",
                "ticket",
                "travel",
                "traveloc",
                "trip",
                "vacat"
              ],
              "name": "travel",
              "q_idx": 0,
              "question": [
                "We have some travel books. Do you have something specific in mind?",
                "Sorry but the book you have in mind is not available!"
              ]
            },
            {
              "degree": "subcategory",
              "keywords": [
                "alias",
                "aliasbaseb",
                "aliasbasketb",
                "aliasfootb",
                "aliasgolf",
                "aliashockey",
                "aliasmotor",
                "aliasrugbi",
                "actor",
                "actress",
                "afghan",
                "africa",
                "african",
                "air",
                "america",
                "american",
                "armyarmi",
                "asiaasia",
                "asian",
                "baseb",
                "basketb",
                "biographi",
                "box",
                "branch",
                "britain",
                "british",
                "buddhism",
                "buddhismbuddhist",
                "canada",
                "canadian",
                "cathol",
                "catholicismcathol",
                "celtic",
                "christian",
                "cinema",
                "civil",
                "cold",
                "comedian",
                "compo",
                "director",
                "directorsfilm",
                "east",
                "eastern",
                "eastmiddl",
                "egypt",
                "egyptian",
                "entertain",
                "europ",
                "european",
                "footbal",
                "forc",
                "forceair",
                "formula",
                "france",
                "french",
                "generale",
                "german",
                "germany",
                "golf",
                "grand",
                "great",
                "greece",
                "greek",
                "head",
                "hindu",
                "hinduism",
                "hip",
                "hiphop",
                "hiphoprap",
                "hockey",
                "hop",
                "ii",
                "iiworld",
                "iran",
                "iranian",
                "iraq",
                "iraqi",
                "ireland",
                "irish",
                "islam",
                "islamist",
                "isra",
                "israel",
                "itali",
                "italian",
                "iworld",
                "judaismjuda",
                "kingdom",
                "latin",
                "marin",
                "marinesmarin",
                "mexican",
                "mexico",
                "middl",
                "minist",
                "ministersunit",
                "motion",
                "motor",
                "movi",
                "musician",
                "nascar",
                "navynavi",
                "of",
                "one",
                "ottoman",
                "palestin",
                "palestinian",
                "peopl",
                "pictur",
                "portug",
                "portugal",
                "portugu",
                "presid",
                "presidentsunit",
                "prime",
                "prix",
                "punk",
                "rap",
                "rapper",
                "read",
                "religi",
                "revolut",
                "rock",
                "rocker",
                "rockpunk",
                "roman",
                "rome",
                "romeitali",
                "rugbi",
                "russia",
                "russian",
                "soccer",
                "south",
                "spain",
                "spanish",
                "sport",
                "state",
                "syria",
                "syrian",
                "turkey",
                "uk",
                "us",
                "vietnam",
                "war",
                "warafghan",
                "warcivil",
                "warcold",
                "wariraq",
                "warvietnam",
                "world",
                "ww"
              ],
              "name": "Bio",
              "q_idx": 0,
              "question": [
                "We have some biographies books. Do you have something specific in mind?"
              ]
            },
            {
              "degree": "subcategory",
              "keywords": [
                "amateur",
                "anim",
                "assassin",
                "bake",
                "beach",
                "british",
                "cat",
                "comedi",
                "conspiraci",
                "cook",
                "craft",
                "crime",
                "dark",
                "detect",
                "disturb",
                "dog",
                "fbi",
                "femal",
                "food",
                "fun",
                "heist",
                "hitman",
                "hobbi",
                "hors",
                "investig",
                "island",
                "justic",
                "killer",
                "knit",
                "mafia",
                "mob",
                "mountain",
                "murder",
                "mysteri",
                "noir",
                "organ",
                "paranorm",
                "pet",
                "polic",
                "privat",
                "protagonist",
                "psychic",
                "quilt",
                "raci",
                "robberi",
                "scari",
                "serial",
                "shapeshift",
                "small",
                "space",
                "suburban",
                "telepathi",
                "theft",
                "thief",
                "town",
                "urban",
                "vampir",
                "veng",
                "vigilant",
                "werewolf",
                "yakuza"
              ],
              "name": "mystery",
              "q_idx": 0,
              "question": [
                "We have some mystery books. Do you have something specific in mind?",
                "Sorry we do not have that book can you look for something else?"
              ]
            },
            {
              "degree": "subcategory",
              "keywords": [
                "romance",
                "age",
                "aisartifici",
                "aliensalien",
                "android",
                "androidsrobot",
                "angel",
                "apollo",
                "armor",
                "arthurian",
                "athena",
                "camelot",
                "clonesclon",
                "colonizationcolon",
                "come",
                "contactcontact",
                "corporationscorpor",
                "corsair",
                "cyberpunkcyberpunk",
                "demonsdemon",
                "devil",
                "dragon",
                "dragonsdragon",
                "druid",
                "elv",
                "empireempir",
                "engineeringgen",
                "excalibur",
                "explorationexplor",
                "fae",
                "faeelf",
                "fairi",
                "finland",
                "fleetfleet",
                "galact",
                "genet",
                "ghostsghost",
                "god",
                "goddessesd",
                "horrorhorror",
                "humorhumor",
                "includ",
                "intellig",
                "invasioninvas",
                "irst",
                "lancelot",
                "legend",
                "lien",
                "love",
                "magic",
                "marin",
                "marinetroop",
                "merlin",
                "metaphys",
                "militari",
                "mutantsmut",
                "mysterymysteri",
                "myth",
                "nonromanticdo",
                "nordic",
                "nors",
                "not",
                "odin",
                "of",
                "olympu",
                "or",
                "pantheon",
                "piratespir",
                "privat",
                "psychicspsych",
                "quest",
                "read",
                "republ",
                "robot",
                "roman",
                "romangreek",
                "romanticrom",
                "shaman",
                "shiftersshapeshift",
                "soldier",
                "sorceri",
                "sorcerysword",
                "space",
                "spirit",
                "spiritu",
                "starship",
                "superherosuperhero",
                "swedish",
                "sword",
                "telepath",
                "theolog",
                "thor",
                "thrillerthril",
                "vampir",
                "vikingvik",
                "visionari",
                "visionarymetaphys",
                "warlock",
                "werewolv",
                "witch",
                "wizard",
                "wizardswitch",
                "zeu"
              ],
              "name": "Scifi",
              "q_idx": 0,
              "question": [
                "We have some Scifi books. Do you have something specific in mind?",
                "Sorry we do not have that book can you look for something else?"
              ]
            }
          ],
          "degree": "category",
          "keywords": [
            "afterword",
            "antholog",
            "authorhous",
            "autobiographi",
            "bestsel",
            "biographi",
            "book",
            "booklist",
            "booklockercom",
            "chase",
            "conspiraci",
            "cookbook",
            "darin",
            "diari",
            "doomsday",
            "edit",
            "hardback",
            "hardbound",
            "hardcov",
            "kimberla",
            "lace",
            "lawson",
            "manuscript",
            "memoir",
            "nonfict",
            "novel",
            "novelett",
            "novella",
            "paperback",
            "penguin",
            "read",
            "reader",
            "reagan",
            "robi",
            "strauss",
            "tome",
            "unpublish",
            "vermeer",
            "vike",
            "ya"
          ],
          "name": "book",
          "q_idx": 0,
          "question": [
            "What kind of books do you read?",
			"Sorry we only have Scifi, romance and travel books!"
          ]
        },
        {
          "children": [
            {
              "degree": "subcategory",
              "keywords": [
                "bedroom",
                "boot",
                "booti",
                "choo",
                "chuck",
                "cleat",
                "clog",
                "dansko",
                "flat",
                "flip",
                "flipflop",
                "flop",
                "footwear",
                "heel",
                "high",
                "hike",
                "insol",
                "jimmi",
                "leather",
                "loafer",
                "nike",
                "on",
                "plimsol",
                "reebok",
                "rubber",
                "sandal",
                "shoe",
                "slip",
                "slipper",
                "sneaker",
                "sock",
                "sole",
                "stiletto",
                "strappi",
                "taylor",
                "tenni",
                "timberland",
                "wear"
              ],
              "name": "shoes",
              "q_idx": 0,
              "question": [
                "What brand of shoes are you looking for?"
              ]
            },
            {
              "degree": "subcategory",
              "keywords": [
                "baggi",
                "boxer",
                "britch",
                "brocad",
                "brown",
                "corduroy",
                "cutoff",
                "denim",
                "elast",
                "gaucho",
                "gray",
                "hoodi",
                "hose",
                "jean",
                "jog",
                "knicker",
                "laci",
                "leg",
                "loafer",
                "metal",
                "pant",
                "panti",
                "polo",
                "shirt",
                "short",
                "skinni",
                "slack",
                "sock",
                "stretchi",
                "sweat",
                "sweatpant",
                "thong",
                "tight",
                "tighti",
                "trouser",
                "underp",
                "undershort",
                "underwear",
                "undi",
                "waist",
                "whiti"
              ],
              "name": "pants",
              "q_idx": 0,
              "question": [
                "What brand of pants are you looking for?"
              ]
            },
            {
              "degree": "subcategory",
              "keywords": [
                "blazer",
                "bomber",
                "cardigan",
                "carhartt",
                "coat",
                "denim",
                "flannel",
                "fleec",
                "gray",
                "hood",
                "hoodi",
                "jacket",
                "khaki",
                "leather",
                "overcoat",
                "pant",
                "parka",
                "plaid",
                "polo",
                "puffer",
                "quilt",
                "raincoat",
                "shirt",
                "sportcoat",
                "sued",
                "sweat",
                "sweater",
                "sweatshirt",
                "trench",
                "turtleneck",
                "vest",
                "waistcoat",
                "waterproof",
                "windbreak",
                "windcheat"
              ],
              "name": "jackets",
              "q_idx": 0,
              "question": [
                "What brand of jackets are you looking for?"
              ]
            }
          ],
          "degree": "category",
          "keywords": [
            "attir",
            "backless",
            "baggi",
            "bath",
            "bedroom",
            "blazer",
            "blous",
            "bomber",
            "boot",
            "booti",
            "boxer",
            "britch",
            "brocad",
            "brown",
            "cardigan",
            "carhartt",
            "choo",
            "chuck",
            "cleat",
            "clog",
            "cloth",
            "coat",
            "corduroy",
            "cutoff",
            "dansko",
            "denim",
            "design",
            "dress",
            "dud",
            "elast",
            "fanci",
            "fashion",
            "flannel",
            "flat",
            "fleec",
            "flip",
            "flipflop",
            "flop",
            "footwear",
            "garment",
            "gaucho",
            "gray",
            "hat",
            "heel",
            "high",
            "hike",
            "hood",
            "hoodi",
            "hose",
            "insol",
            "jacket",
            "jean",
            "jimmi",
            "jog",
            "khaki",
            "knicker",
            "laci",
            "lauren",
            "leather",
            "leg",
            "loafer",
            "metal",
            "mitten",
            "muumuu",
            "nightgown",
            "nighti",
            "nike",
            "on",
            "overcoat",
            "pajama",
            "pant",
            "panti",
            "parka",
            "plaid",
            "plimsol",
            "polo",
            "prom",
            "puffer",
            "quilt",
            "raincoat",
            "ralph",
            "reebok",
            "rubber",
            "sandal",
            "scarv",
            "shirt",
            "shoe",
            "short",
            "skinni",
            "slack",
            "slip",
            "slipper",
            "sneaker",
            "sock",
            "soil",
            "sole",
            "sportcoat",
            "stiletto",
            "strappi",
            "stretchi",
            "sued",
            "suit",
            "sweat",
            "sweater",
            "sweatpant",
            "sweatshirt",
            "taylor",
            "tenni",
            "tent",
            "thong",
            "tight",
            "tighti",
            "timberland",
            "tog",
            "trench",
            "trouser",
            "turtleneck",
            "undercloth",
            "undergar",
            "underp",
            "undershort",
            "underwear",
            "undi",
            "uniform",
            "vest",
            "waist",
            "waistcoat",
            "wardrob",
            "waterproof",
            "wear",
            "whiti",
            "windbreak",
            "windcheat",
            "winter"
          ],
          "name": "clothes",
          "q_idx": 0,
          "question": [
            "What clothing are you looking for?",
            "Sorry we only have pants, shoes and jackets!"
          ]
        }
      ],
      "degree": "main2",
      "keywords": [
        "love",
        "romance",
        "aliasbaseb",
        "aliasgolf",
        "aliashockey",
        "aliasmotor",
        "aliasrugbi",
        "acer",
        "actor",
        "actress",
        "actressesactor",
        "afghan",
        "africaafrica",
        "african",
        "age",
        "agenc",
        "air",
        "airfar",
        "airlin",
        "aisartifici",
        "aliensalien",
        "alienwar",
        "amateur",
        "america",
        "americalatin",
        "american",
        "android",
        "androidsrobot",
        "angel",
        "anim",
        "apollo",
        "appl",
        "armor",
        "armyarmi",
        "arthurian",
        "asiaasia",
        "asian",
        "aspir",
        "assassin",
        "assign",
        "athena",
        "attir",
        "axim",
        "backless",
        "baggi",
        "bake",
        "baseb",
        "basketb",
        "bath",
        "beach",
        "bedroom",
        "biographi",
        "blazer",
        "blous",
        "bomber",
        "book",
        "boot",
        "booti",
        "box",
        "boxer",
        "branch",
        "britain",
        "britch",
        "british",
        "brocad",
        "brown",
        "buddhism",
        "buddhist",
        "budget",
        "busi",
        "camelot",
        "canadacanada",
        "canadian",
        "cardigan",
        "carhartt",
        "cat",
        "cathol",
        "catholic",
        "celtic",
        "channel",
        "cheap",
        "choo",
        "christian",
        "chuck",
        "cinema",
        "civil",
        "cleat",
        "clog",
        "clonesclon",
        "cloth",
        "coat",
        "cold",
        "colonization",
        "come",
        "comedi",
        "comedian",
        "compani",
        "compaq",
        "compo",
        "comput",
        "confer",
        "conspiraci",
        "contact",
        "cook",
        "corduroy",
        "corporation",
        "corsair",
        "craft",
        "crime",
        "cutoff",
        "cyberpunk",
        "dansko",
        "dark",
        "dell",
        "demonsdemon",
        "denim",
        "design",
        "destin",
        "detect",
        "devil",
        "dimens",
        "director",
        "directorsfilm",
        "disturb",
        "dog",
        "dragon",
        "dress",
        "druid",
        "dud",
        "dv",
        "east",
        "eastern",
        "eastmiddl",
        "edg",
        "egypt",
        "egyptian",
        "elast",
        "elv",
        "empire",
        "engineering",
        "entertain",
        "europ",
        "european",
        "excalibur",
        "exploration",
        "fae",
        "faeelf",
        "fairi",
        "fanci",
        "fare",
        "fashion",
        "fbi",
        "femal",
        "finland",
        "flannel",
        "flat",
        "fleec",
        "fleet",
        "flight",
        "flip",
        "flipflop",
        "flop",
        "food",
        "footb",
        "footbal",
        "footwear",
        "forc",
        "forceair",
        "formula",
        "francefr",
        "french",
        "fujitsu",
        "fun",
        "galact",
        "game",
        "garment",
        "gaucho",
        "generaleurop",
        "genet",
        "german",
        "germany",
        "ghost",
        "god",
        "goddess",
        "golf",
        "grand",
        "gray",
        "great",
        "greece",
        "greek",
        "halo",
        "hat",
        "head",
        "heel",
        "heist",
        "high",
        "hike",
        "hindu",
        "hinduism",
        "hip",
        "hiphop",
        "hiphoprap",
        "hitman",
        "hobbi",
        "hockey",
        "holiday",
        "homework",
        "hood",
        "hoodi",
        "hop",
        "horror",
        "hors",
        "hose",
        "hotel",
        "hp",
        "humorhumor",
        "ibm",
        "ibook",
        "ii",
        "iiworld",
        "includ",
        "insol",
        "inspiron",
        "intellig",
        "invasioninvas",
        "investig",
        "iran",
        "iranian",
        "iraq",
        "iraqi",
        "irelandireland",
        "irish",
        "irst",
        "islam",
        "islamist",
        "island",
        "isra",
        "israel",
        "itali",
        "italian",
        "iworld",
        "jacket",
        "jean",
        "jimmi",
        "job",
        "jog",
        "judaismjuda",
        "justic",
        "khaki",
        "killer",
        "kingdom",
        "knicker",
        "knit",
        "laci",
        "lancelot",
        "laptop",
        "last",
        "latin",
        "latitud",
        "lauren",
        "leather",
        "lectur",
        "leg",
        "legendsgreek",
        "legendsnors",
        "lenovo",
        "lien",
        "loafer",
        "love",
        "macbook",
        "mafia",
        "magic",
        "marin",
        "marinesmarin",
        "marinetroop",
        "merlin",
        "metal",
        "metaphys",
        "mexican",
        "mexico",
        "middl",
        "militari",
        "minist",
        "ministersunit",
        "minut",
        "mitten",
        "mob",
        "motion",
        "motor",
        "mountain",
        "movi",
        "mp",
        "murder",
        "musician",
        "mutantsmut",
        "muumuu",
        "mx",
        "mysteri",
        "mystery",
        "myth",
        "nascar",
        "navynavi",
        "nc",
        "netbook",
        "news",
        "nightgown",
        "nighti",
        "nike",
        "noir",
        "nonromanticdo",
        "nordic",
        "nors",
        "not",
        "note",
        "notebook",
        "odin",
        "of",
        "offic",
        "olympu",
        "on",
        "one",
        "or",
        "organ",
        "ottoman",
        "overcoat",
        "packag",
        "pajama",
        "palestin",
        "palestinian",
        "pant",
        "pantheon",
        "panti",
        "paranorm",
        "parka",
        "pavilion",
        "pc",
        "peopl",
        "pet",
        "pictur",
        "piratespir",
        "plaid",
        "plane",
        "play",
        "player",
        "plimsol",
        "polic",
        "polo",
        "portug",
        "portugalspain",
        "portugu",
        "powerbook",
        "presid",
        "presidentsunit",
        "prime",
        "privat",
        "prix",
        "pro",
        "prom",
        "protagonist",
        "psychic",
        "psychics",
        "puffer",
        "punk",
        "quest",
        "quilt",
        "raci",
        "raincoat",
        "ralph",
        "rap",
        "rapper",
        "read",
        "redempt",
        "reebok",
        "religi",
        "republ",
        "research",
        "revolut",
        "revolution",
        "robberi",
        "robot",
        "rock",
        "rocker",
        "rockpunk",
        "roman",
        "romantic",
        "rome",
        "romeitali",
        "rubber",
        "rugbi",
        "russian",
        "russia",
        "sandal",
        "scari",
        "scarv",
        "school",
        "serial",
        "shaman",
        "shapeshift",
        "shirt",
        "shoe",
        "short",
        "site",
        "skinni",
        "slack",
        "slip",
        "slipper",
        "small",
        "sneaker",
        "soccer",
        "sock",
        "soil",
        "soldier",
        "sole",
        "soni",
        "sorceri",
        "sorcerysword",
        "south",
        "space",
        "spain",
        "spanish",
        "spirit",
        "spiritu",
        "sport",
        "sportcoat",
        "starship",
        "state",
        "stiletto",
        "strappi",
        "stretchi",
        "student",
        "studi",
        "studio",
        "suburban",
        "sued",
        "suit",
        "superhero",
        "sweat",
        "sweater",
        "sweatpant",
        "sweatshirt",
        "swedish",
        "sword",
        "syria",
        "syrian",
        "taylor",
        "telepath",
        "telepathi",
        "tenni",
        "tent",
        "theft",
        "theolog",
        "thief",
        "thinkpad",
        "thong",
        "thor",
        "thriller",
        "ticket",
        "tight",
        "tighti",
        "timberland",
        "timelin",
        "tog",
        "town",
        "travel",
        "traveloc",
        "trench",
        "trip",
        "trouser",
        "turkey",
        "turtleneck",
        "tutori",
        "twitch",
        "uk",
        "ultraport",
        "undercloth",
        "undergar",
        "underp",
        "undershort",
        "underwear",
        "undi",
        "uniform",
        "univers",
        "urban",
        "us",
        "vacat",
        "vaio",
        "vampir",
        "veng",
        "vest",
        "vietnam",
        "vigilant",
        "vikingvik",
        "visionari",
        "visionary",
        "waist",
        "waistcoat",
        "war",
        "warafghan",
        "warcivil",
        "warcold",
        "wardrob",
        "wariraq",
        "warlock",
        "warvietnam",
        "waterproof",
        "wear",
        "werewolf",
        "werewolv",
        "whiti",
        "windbreak",
        "windcheat",
        "winter",
        "witch",
        "witcher",
        "wizard",
        "wizardswitch",
        "work",
        "world",
        "ww",
        "xv",
        "yakuza",
        "zeu"
      ],
      "name": "product",
      "q_idx": 0,
      "question": [
        "What products are you interested in?"
      ]
    },
    {
      "children": [
        {
          "children": [
            {
              "children": [
                {
                  "degree": "general_child",
                  "keywords": [
                    "aerob",
                    "basebal",
                    "freshwat",
                    "rubix",
                    "unspecified",
                    "abandon",
                    "abus",
                    "act",
                    "activ",
                    "advoc",
                    "aeromodel",
                    "aid",
                    "air",
                    "airbrush",
                    "aircraft",
                    "airsoft",
                    "album",
                    "amateur",
                    "an",
                    "analysi",
                    "anim",
                    "animalspetsdog",
                    "antiqu",
                    "aquarium",
                    "archeri",
                    "arrang",
                    "art",
                    "artwork",
                    "astrolog",
                    "astronomi",
                    "babi",
                    "backgammon",
                    "badminton",
                    "balanc",
                    "balloon",
                    "base",
                    "basebal",
                    "basketbal",
                    "beachsun",
                    "beachcomb",
                    "beadwork",
                    "beatbox",
                    "becom",
                    "beer",
                    "bell",
                    "belli",
                    "bicycl",
                    "bike",
                    "bird",
                    "blacksmith",
                    "blog",
                    "bmx",
                    "board",
                    "boardgam",
                    "boat",
                    "bodi",
                    "bonsai",
                    "bookbind",
                    "boomerang",
                    "bowl",
                    "break",
                    "brew",
                    "bridg",
                    "bring",
                    "build",
                    "butterfli",
                    "button",
                    "cake",
                    "calligraphi",
                    "camp",
                    "candl",
                    "cano",
                    "car",
                    "card",
                    "cartoon",
                    "casino",
                    "castl",
                    "cave",
                    "ceram",
                    "chase",
                    "cheerlead",
                    "chemistri",
                    "chess",
                    "child",
                    "children",
                    "choir",
                    "churchchurch",
                    "cigar",
                    "climb",
                    "cloud",
                    "coil",
                    "coin",
                    "collect",
                    "color",
                    "compos",
                    "comput",
                    "conworld",
                    "cook",
                    "cosplay",
                    "cours",
                    "craft",
                    "crochet",
                    "crossstitch",
                    "crossword",
                    "cube",
                    "cube",
                    "danc",
                    "dart",
                    "decor",
                    "defens",
                    "detect",
                    "diecast",
                    "digit",
                    "disabl",
                    "dive",
                    "dodgebal",
                    "doll",
                    "dollhous",
                    "domino",
                    "draw",
                    "dumpster",
                    "eat",
                    "educ",
                    "elderli",
                    "electron",
                    "embroideri",
                    "engin",
                    "entertain",
                    "event",
                    "exercis",
                    "explor",
                    "fair",
                    "falconri",
                    "family",
                    "fast",
                    "felt",
                    "fenc",
                    "figur",
                    "fire",
                    "fish",
                    "fli",
                    "floorbal",
                    "floral",
                    "food",
                    "footbal",
                    "for",
                    "foreign",
                    "four",
                    "freshwat",
                    "friendsneighbor",
                    "frisbe",
                    "frolf",
                    "gambl",
                    "game",
                    "garag",
                    "garden",
                    "genealog",
                    "geocach",
                    "ghost",
                    "glide",
                    "glowstick",
                    "gnome",
                    "go",
                    "golf",
                    "grip",
                    "guitar",
                    "gun",
                    "gunsmith",
                    "gymnast",
                    "gyotaku",
                    "habitat",
                    "handwrit",
                    "hang",
                    "hat",
                    "helicopt",
                    "herp",
                    "hike",
                    "hockey",
                    "home",
                    "hoop",
                    "hors",
                    "hot",
                    "hous",
                    "hula",
                    "human",
                    "hunt",
                    "icesk",
                    "illus",
                    "imperson",
                    "in",
                    "instrument",
                    "internet",
                    "invent",
                    "jet",
                    "jewelri",
                    "jigsaw",
                    "journal",
                    "juggl",
                    "jump",
                    "kart",
                    "kayak",
                    "keep",
                    "kitchen",
                    "kite",
                    "knit",
                    "knot",
                    "lacross",
                    "languag",
                    "laser",
                    "lawn",
                    "learn",
                    "leathercraft",
                    "lego",
                    "letterbox",
                    "line",
                    "listen",
                    "locksport",
                    "macram",
                    "magic",
                    "make",
                    "marksmanship",
                    "martial",
                    "matchstick",
                    "medit",
                    "metal",
                    "microscopi",
                    "model",
                    "motorcycl",
                    "mountain",
                    "movi",
                    "music",
                    "nail",
                    "needlepoint",
                    "on",
                    "or",
                    "origami",
                    "out",
                    "own",
                    "paint",
                    "paintbal",
                    "pantri",
                    "papermach",
                    "papermak",
                    "parachut",
                    "paraglid",
                    "parkour",
                    "peopl",
                    "photographi",
                    "piano",
                    "pigeon",
                    "pilot",
                    "pinochl",
                    "pipe",
                    "plane",
                    "plank",
                    "play",
                    "poi",
                    "poker",
                    "pole",
                    "polo",
                    "potteri",
                    "power",
                    "powerbok",
                    "protest",
                    "puppetri",
                    "puzzl",
                    "pyrotechn",
                    "quilt",
                    "rc",
                    "race",
                    "radio",
                    "raft",
                    "railfan",
                    "railroad",
                    "rap",
                    "read",
                    "record",
                    "relax",
                    "renaiss",
                    "rent",
                    "repair",
                    "rescu",
                    "ride",
                    "ring",
                    "robot",
                    "rock",
                    "rocket",
                    "roleplay",
                    "rope",
                    "rpm",
                    "rub",
                    "run",
                    "sale",
                    "saltwat",
                    "saltwater",
                    "sand",
                    "scrapbook",
                    "scuba",
                    "self",
                    "sew",
                    "shark",
                    "ship",
                    "shoot",
                    "shop",
                    "sing",
                    "skateboard",
                    "skeet",
                    "sketch",
                    "ski",
                    "sky",
                    "slack",
                    "sleep",
                    "slingshot",
                    "slot",
                    "smoke",
                    "snorkel",
                    "snowboard",
                    "soap",
                    "soccer",
                    "social",
                    "song",
                    "speed",
                    "spelunk",
                    "spend",
                    "sport",
                    "spot",
                    "stamp",
                    "storm",
                    "storytel",
                    "strength",
                    "string",
                    "surf",
                    "surviv",
                    "swim",
                    "sword",
                    "tan",
                    "tast",
                    "tat",
                    "taxidermi",
                    "tea",
                    "team",
                    "tenni",
                    "tesla",
                    "tetri",
                    "text",
                    "textil",
                    "the",
                    "theater",
                    "tie",
                    "time",
                    "to",
                    "tombston",
                    "tool",
                    "toy",
                    "train",
                    "travel",
                    "treasur",
                    "tree",
                    "trekki",
                    "tutor",
                    "tv",
                    "ultim",
                    "urban",
                    "video",
                    "violin",
                    "volunt",
                    "walk",
                    "warhamm",
                    "watch",
                    "watcher",
                    "weather",
                    "weightlift",
                    "weights",
                    "wheel",
                    "windsurf",
                    "wine",
                    "wingsuit",
                    "with",
                    "woodwork",
                    "work",
                    "world",
                    "wrestl",
                    "write",
                    "yoga",
                    "yoyo",
                    "ziplin",
                    "zumba"
                  ],
                  "name": "question3",
                  "q_idx": 0,
                  "question": [
                    "what is your budget?"
                  ]
                }
              ],
              "degree": "general_child",
              "keywords": [
                "agricultur",
                "aircraft",
                "analyst",
                "artist",
                "cafeteria",
                "chemic",
                "commerci",
                "commercial",
                "computers",
                "corporate",
                "cpa",
                "detective",
                "drafter",
                "fast",
                "finance",
                "fish",
                "foreign",
                "freight",
                "ga",
                "government",
                "hair",
                "hotel",
                "inform",
                "instruments",
                "journalist",
                "lpn",
                "manufacturing",
                "md",
                "mechan",
                "medic",
                "military",
                "orthopedist",
                "pa",
                "plumb",
                "print",
                "prison",
                "privat",
                "psycholog",
                "publications",
                "radio",
                "religi",
                "restaurant",
                "safeti",
                "school",
                "short",
                "telecommunications",
                "teleconferencing",
                "transit",
                "utilities",
                "vineyard",
                "vmd",
                "volunteer",
                "author",
                "ac",
                "abl",
                "abus",
                "account",
                "adjust",
                "administr",
                "admiralti",
                "admiss",
                "adult",
                "advertis",
                "advertising",
                "advis",
                "advisor",
                "aeronaut",
                "aerospac",
                "affair",
                "agenc",
                "agent",
                "agricultur",
                "aid",
                "air",
                "aircraft",
                "airfield",
                "airlin",
                "airlines",
                "airport",
                "alarm",
                "alcohol",
                "alumni",
                "ambul",
                "amus",
                "analysi",
                "analyst",
                "and",
                "anesthesiologist",
                "anim",
                "announc",
                "answer",
                "anthropolog",
                "antiterror",
                "apparel",
                "appeal",
                "applianc",
                "applic",
                "apprais",
                "aquaculturist",
                "aquarium",
                "aquat",
                "arc",
                "archeolog",
                "architect",
                "architectur",
                "archivist",
                "area",
                "armor",
                "arrang",
                "art",
                "artilleri",
                "artist",
                "arts",
                "assault",
                "assembl",
                "assessor",
                "assist",
                "athlet",
                "athletes",
                "atm",
                "atmospher",
                "attend",
                "audiovisu",
                "audiovisu",
                "auditor",
                "auto",
                "automobil",
                "automot",
                "avion",
                "baggag",
                "baker",
                "ballist",
                "bank",
                "banking",
                "batchmak",
                "bellhop",
                "benefit",
                "bicycl",
                "bill",
                "binderi",
                "biolog",
                "biologist",
                "biomed",
                "bleach",
                "blind",
                "blower",
                "boat",
                "bodi",
                "bond",
                "book",
                "border",
                "boss",
                "boy",
                "branch",
                "brattic",
                "breeder",
                "bridg",
                "broadcast",
                "broker",
                "broker",
                "brokerag",
                "bu",
                "budget",
                "build",
                "builder",
                "bulldoz",
                "busi",
                "buyer",
                "cabinet",
                "cad",
                "cage",
                "camp",
                "caption",
                "cardiologist",
                "cardiopulmonari",
                "care",
                "career",
                "cargo",
                "carpent",
                "carpenter",
                "carpet",
                "carrier",
                "cartograph",
                "cartoonist",
                "case",
                "casework",
                "cashier",
                "casino",
                "cast",
                "cater",
                "ceil",
                "cement",
                "center",
                "ceram",
                "certifi",
                "chaplain",
                "charter",
                "chauffeur",
                "chemic",
                "chemistri",
                "chief",
                "child",
                "citi",
                "civil",
                "claim",
                "clergi",
                "clerk",
                "clinic",
                "coach",
                "coatroom",
                "collect",
                "collector",
                "colleg",
                "collegeunivers",
                "comment",
                "commerci",
                "commiss",
                "commun",
                "compens",
                "complianc",
                "comput",
                "conductor",
                "congression",
                "conserv",
                "conservationist",
                "construct",
                "consult",
                "contract",
                "contractor",
                "control",
                "conventionev",
                "cook",
                "coordin",
                "copi",
                "corp",
                "corpor",
                "correct",
                "correspond",
                "cosmetologist",
                "cost",
                "costum",
                "counsel",
                "counselor",
                "counter",
                "counti",
                "country",
                "courier",
                "cours",
                "court",
                "craft",
                "crane",
                "credit",
                "crew",
                "crimin",
                "crop",
                "cross",
                "cultur",
                "curat",
                "custom",
                "cut",
                "cutter",
                "dairi",
                "damage",
                "data",
                "databas",
                "deaf",
                "dealer",
                "deliveri",
                "demonstr",
                "dental",
                "dentist",
                "depart",
                "dermatologist",
                "design",
                "desk",
                "desktop",
                "detect",
                "develop",
                "development",
                "devic",
                "die",
                "dietet",
                "dietitian",
                "director",
                "directori",
                "directorsmanag",
                "disabl",
                "diseas",
                "disk",
                "dispatch",
                "display",
                "dispos",
                "distanc",
                "distribut",
                "diver",
                "doctor",
                "door",
                "drafter",
                "drama",
                "draperi",
                "dress",
                "dri",
                "driller",
                "driver",
                "drug",
                "drugs",
                "duti",
                "dye",
                "econom",
                "economist",
                "editor",
                "editori",
                "educ",
                "eeg",
                "electr",
                "electromechan",
                "electromechan",
                "electron",
                "elementari",
                "elev",
                "elig",
                "emerg",
                "employ",
                "employe",
                "energi",
                "enforc",
                "engin",
                "english",
                "engrav",
                "entertain",
                "environment",
                "equal",
                "equip",
                "equipment",
                "espionag",
                "estat",
                "estim",
                "etcher",
                "ethnic",
                "event",
                "examin",
                "examinercoron",
                "excav",
                "exchang",
                "execut",
                "exercis",
                "exhibit",
                "expedit",
                "experiment",
                "expert",
                "explos",
                "export",
                "fabric",
                "facil",
                "factor",
                "factori",
                "famili",
                "farm",
                "farmer",
                "farmer",
                "farmwork",
                "fashion",
                "feeder",
                "fenc",
                "field",
                "fight",
                "file",
                "filer",
                "filler",
                "film",
                "financ",
                "financi",
                "fine",
                "finish",
                "fire",
                "fish",
                "fisheri",
                "fisherman",
                "fit",
                "flight",
                "floor",
                "floral",
                "food",
                "food",
                "for",
                "forc",
                "foreign",
                "forens",
                "forest",
                "forestri",
                "forg",
                "forklift",
                "fraud",
                "freight",
                "fuel",
                "fund",
                "funer",
                "furnishings",
                "furnitur",
                "ga",
                "game",
                "gener",
                "geographi",
                "geolog",
                "geologist",
                "girl",
                "glass",
                "glu",
                "golf",
                "govern",
                "grader",
                "graduat",
                "graphic",
                "greenhous",
                "grinder",
                "groomer",
                "guard",
                "guid",
                "guidanc",
                "gynecologist",
                "hand",
                "handl",
                "handler",
                "harbor",
                "hardwar",
                "hardwood",
                "hatcheri",
                "hazard",
                "health",
                "hear",
                "heat",
                "heavi",
                "high",
                "highway",
                "histor",
                "histori",
                "home",
                "horticultur",
                "horticulturist",
                "hospit",
                "hospital",
                "host",
                "hostess",
                "hotel",
                "household",
                "housekeep",
                "human",
                "husbandri",
                "hydraul",
                "hygienist",
                "identif",
                "illustr",
                "immigr",
                "impair",
                "industri",
                "industrial",
                "industrialorganiz",
                "infantri",
                "inform",
                "inspector",
                "instal",
                "institut",
                "instruct",
                "instructor",
                "instrument",
                "insul",
                "insur",
                "intellig",
                "interior",
                "intern",
                "internist",
                "interpret",
                "interview",
                "inventori",
                "investig",
                "irradiatedfuel",
                "irrig",
                "it",
                "janitori",
                "job",
                "jockey",
                "joiner",
                "judg",
                "justic",
                "keeper",
                "kennel",
                "kindergarten",
                "labor",
                "laboratori",
                "lake",
                "landscap",
                "languag",
                "laser",
                "lath",
                "launch",
                "law",
                "lawyer",
                "layout",
                "leader",
                "leader",
                "legal",
                "legisl",
                "librari",
                "licens",
                "life",
                "light",
                "line",
                "linguist",
                "literaci",
                "literatur",
                "livestock",
                "loan",
                "lobbi",
                "lock",
                "locomot",
                "log",
                "long",
                "lot",
                "lyricist",
                "machin",
                "machineri",
                "magazin",
                "mail",
                "mainten",
                "maker",
                "makeup",
                "manag",
                "manager",
                "manicurist",
                "manual",
                "map",
                "marbl",
                "marin",
                "marina",
                "marineport",
                "mark",
                "marker",
                "market",
                "marriag",
                "mason",
                "massag",
                "master",
                "mate",
                "materi",
                "math",
                "mathemat",
                "mathematician",
                "maxillofaci",
                "measur",
                "meat",
                "mechan",
                "medic",
                "medicin",
                "member",
                "mental",
                "merchandis",
                "messeng",
                "metal",
                "meter",
                "middl",
                "militari",
                "militaryenlist",
                "mill",
                "mine",
                "miss",
                "missil",
                "missionari",
                "model",
                "monitor",
                "motel",
                "motion",
                "motor",
                "motorboat",
                "motorcycl",
                "municip",
                "museum",
                "music",
                "musician",
                "narcot",
                "naturalist",
                "new",
                "news",
                "newscast",
                "newspap",
                "newspapermagazin",
                "nonretail",
                "nuclear",
                "numer",
                "nurs",
                "nurse",
                "nurseri",
                "nutritionist",
                "observ",
                "obstetrician",
                "occup",
                "oceanograph",
                "of",
                "offbear",
                "offic",
                "offset",
                "oper",
                "ophthalm",
                "ophthalmologist",
                "opportun",
                "or",
                "oral",
                "orchestr",
                "order",
                "ordinari",
                "organ",
                "ornamentalmetalwork",
                "orthodont",
                "orthodontist",
                "outdoor",
                "overhead",
                "packag",
                "packer",
                "painter",
                "park",
                "parol",
                "part",
                "passenger",
                "pasteup",
                "patent",
                "pathologist",
                "patrol",
                "patternmak",
                "payrol",
                "pbx",
                "peac",
                "peacekeep",
                "pediatr",
                "pediatrician",
                "pedicurist",
                "person",
                "personnel",
                "pest",
                "pesticid",
                "petroleum",
                "pharmaci",
                "philosophi",
                "photoopt",
                "photoengrav",
                "photogrammetr",
                "photograph",
                "physic",
                "physician",
                "physician",
                "physiologist",
                "pictur",
                "pilot",
                "pit",
                "placement",
                "plan",
                "planner",
                "plant",
                "plasma",
                "plaster",
                "plastic",
                "platemak",
                "plumber",
                "poet",
                "polic",
                "policecanin",
                "polici",
                "polit",
                "pollut",
                "portabl",
                "porter",
                "postal",
                "postmast",
                "poultri",
                "power",
                "powerlin",
                "practic",
                "practition",
                "precis",
                "prepar",
                "preschool",
                "press",
                "pressur",
                "prevent",
                "print",
                "printer",
                "printinggraph",
                "printmak",
                "privat",
                "probat",
                "process",
                "procur",
                "produc",
                "product",
                "products",
                "profession",
                "professor",
                "professsor",
                "program",
                "programm",
                "programs",
                "projectionist",
                "promot",
                "proofread",
                "prop",
                "properti",
                "prosthet",
                "protect",
                "pruner",
                "psychiatr",
                "psychiatrist",
                "psycholog",
                "psychologist",
                "public",
                "publish",
                "purchas",
                "qualiti",
                "quarri",
                "radar",
                "radiat",
                "radio",
                "radiolog",
                "radiologist",
                "rail",
                "railroad",
                "raiser",
                "rancher",
                "rang",
                "reactor",
                "reader",
                "real",
                "receiv",
                "recondition",
                "record",
                "recoveri",
                "recreat",
                "recruit",
                "recycl",
                "refere",
                "refineri",
                "refriger",
                "refus",
                "region",
                "registrar",
                "rehabilit",
                "relat",
                "reliabl",
                "religi",
                "religion",
                "remedi",
                "remov",
                "rental",
                "repair",
                "report",
                "repres",
                "representit",
                "reproduct",
                "research",
                "reserv",
                "resid",
                "resourc",
                "respiratori",
                "restaur",
                "restor",
                "retail",
                "retard",
                "revenu",
                "room",
                "runner",
                "safeti",
                "sale",
                "salesmen",
                "salesperson",
                "sanitari",
                "saw",
                "scaler",
                "scanner",
                "school",
                "scienc",
                "scientif",
                "scientist",
                "scientist",
                "scout",
                "screen",
                "script",
                "seamen",
                "searcher",
                "secretari",
                "sector",
                "secur",
                "selfenrich",
                "septic",
                "servic",
                "set",
                "setup",
                "setter",
                "sew",
                "sewer",
                "sharpen",
                "sheet",
                "ship",
                "shoe",
                "shovel",
                "show",
                "signal",
                "site",
                "skin",
                "slot",
                "small",
                "social",
                "sociolog",
                "sociologist",
                "softwar",
                "soil",
                "solar",
                "solid",
                "sonar",
                "sorter",
                "sound",
                "space",
                "special",
                "specialist",
                "speech",
                "sport",
                "sportswrit",
                "stain",
                "standard",
                "statement",
                "station",
                "stationari",
                "statist",
                "steel",
                "stock",
                "storag",
                "store",
                "streetcar",
                "stress",
                "structur",
                "stucco",
                "student",
                "studi",
                "stylist",
                "substanc",
                "subway",
                "superintend",
                "supervisor",
                "support",
                "surgeon",
                "surgic",
                "surveil",
                "survey",
                "surveyor",
                "switch",
                "switchboard",
                "system",
                "tailor",
                "talk",
                "tank",
                "tax",
                "taxi",
                "teach",
                "teacher",
                "team",
                "technic",
                "technician",
                "techniciantechnologist",
                "technolog",
                "technologist",
                "technology",
                "telecommun",
                "telephon",
                "teller",
                "tender",
                "tester",
                "testerland",
                "tests",
                "textil",
                "the",
                "theatric",
                "therapi",
                "therapist",
                "ticket",
                "tile",
                "time",
                "timekeep",
                "titl",
                "to",
                "tool",
                "tour",
                "town",
                "tractor",
                "trade",
                "trader",
                "traffic",
                "train",
                "trainer",
                "transcriptionist",
                "transit",
                "translat",
                "transport",
                "travel",
                "treasur",
                "treatment",
                "tree",
                "trimmer",
                "truck",
                "tuner",
                "tv",
                "ultrasound",
                "umpir",
                "underwrit",
                "unemploy",
                "urban",
                "usher",
                "util",
                "vehicl",
                "vehicles",
                "vend",
                "vessel",
                "veterinari",
                "veterinarian",
                "video",
                "vocat",
                "voic",
                "volunt",
                "waiter",
                "waitress",
                "wall",
                "warden",
                "warehous",
                "wast",
                "watch",
                "water",
                "waterway",
                "weather",
                "web",
                "weigher",
                "welder",
                "welfar",
                "wholesal",
                "wildlif",
                "window",
                "woodwork",
                "word",
                "work",
                "worker",
                "writer",
                "yard",
                "yardmast",
                "zoo",
                "zoologist"
              ],
              "name": "question2",
              "q_idx": 0,
              "question": [
                "What are your hobbies?"
              ]
            }
          ],
          "degree": "general_child",
          "keywords": [
            "about",
            "alright",
            "chat",
            "gener",
            "go",
            "let",
            "like",
            "ok",
            "sure",
            "to",
            "what",
            "would",
            "ye",
            "you"
          ],
          "name": "question1",
          "q_idx": 0,
          "question": [
            "What is your occupation?"
          ]
        }
      ],
      "degree": "general",
      "keywords": [
        "alright",
        "am",
        "brows",
        "cool",
        "dont",
        "explor",
        "know",
        "not",
        "ok",
        "okay",
        "specif",
        "sure",
        "whi"
      ],
      "name": "general",
      "q_idx": 0,
      "question": [
        "Lets have a general chat in order to recommend you products."
      ]
    }
  ],
  "degree": "root",
  "keywords": null,
  "name": "browsing",
  "question": [
    "What are you looking for?",
    "Sorry we do not have this product right now, do you have other products you are interested in?"
  ]
}